[
  {
    "StringData": {
            "fontDefault" : "qrc:/Fonts/Nunito/Nunito-Regular.ttf",
            "fontAvenirNextLTPro-Regular" : "qrc:/Fonts/AvenirNextLTPro-Regular.ttf",
            "fontOpen_Sans_Bold" : "qrc:/Fonts/Open_Sans_Bold.ttf",
            "fontMontserrat-Regular" : "qrc:/Fonts/Montserrat-Regular.ttf",
            "fontOpen_Sans_Bold_Italic" : "qrc:/Fonts/Open_Sans_Bold_Italic.ttf",
            "fontOpen_Sans_Italic" : "qrc:/Fonts/Open_Sans_Italic.ttf",
            "fontOpen_Sans_Regular" : "qrc:/Fonts/Open_Sans_Regular.ttf",
            "fontOpen_Sans_Bold" : "qrc:/Fonts/Open Sans Bold.ttf",
            "fontRedHatDisplay-Regular" : "qrc:/Fonts/RedHatDisplay-Regular.ttf",
            "fontRoboto-Regular" : "qrc:/Fonts/Roboto-Regular.ttf",
            "fontSeven_Segment" : "qrc:/Fonts/Seven_Segment.ttf",
            "commlinkSettings" : "Data Link",
            "dashBoardTitle" : "OBD II Simulator",
            "navbarSerialPortTitle" : "Serial Port Setting",
            "exit" : "Exit",
            "about" : "About",
            "disconnect" : "Disconnect",
            "disconnectConfirmation" : "Are you sure you want to disconnect ?",
            "yes": "Yes",
            "no": "No",
            "ok": "Ok",
            "cancel": "Cancel",
            "softwareExit" : "Are you sure you want to exit?",
            "serialPortMessage" : "Serial port is not connected."
    }
  }
]
